injection/__init__.py
injection/__init__.pyi
injection/entrypoint.py
injection/exceptions.py
injection/loaders.py
injection/py.typed
injection/_core/__init__.py
injection/_core/asfunction.py
injection/_core/descriptors.py
injection/_core/injectables.py
injection/_core/locator.py
injection/_core/module.py
injection/_core/scope.py
injection/_core/slots.py
injection/_core/common/__init__.py
injection/_core/common/asynchronous.py
injection/_core/common/event.py
injection/_core/common/invertible.py
injection/_core/common/lazy.py
injection/_core/common/threading.py
injection/_core/common/type.py
injection/ext/__init__.py
injection/ext/fastapi.py
injection/ext/fastapi.pyi
injection/testing/__init__.py
injection/testing/__init__.pyi
python_injection-0.25.14.dist-info/METADATA
python_injection-0.25.14.dist-info/WHEEL
python_injection-0.25.14.dist-info/licenses/LICENSE
python_injection-0.25.14.dist-info/RECORD
