Metadata-Version: 2.4
Name: python-injection
Version: 0.25.14
Summary: Dead-simple dependency injection framework for Python.
Project-URL: Documentation, https://python-injection.remimd.dev
Project-URL: Repository, https://github.com/100nm/python-injection
Author: remimd
License-Expression: MIT
License-File: LICENSE
Keywords: dependencies,dependency,inject,injection
Classifier: Development Status :: 4 - Beta
Classifier: Intended Audience :: Developers
Classifier: Natural Language :: English
Classifier: Operating System :: OS Independent
Classifier: Programming Language :: Python
Classifier: Programming Language :: Python :: 3
Classifier: Programming Language :: Python :: 3 :: Only
Classifier: Programming Language :: Python :: 3.12
Classifier: Programming Language :: Python :: 3.13
Classifier: Programming Language :: Python :: 3.14
Classifier: Topic :: Software Development :: Libraries
Classifier: Topic :: Software Development :: Libraries :: Application Frameworks
Classifier: Topic :: Software Development :: Libraries :: Python Modules
Classifier: Topic :: Software Development :: Testing
Classifier: Typing :: Typed
Requires-Python: <3.15,>=3.12
Requires-Dist: type-analyzer
Provides-Extra: async
Requires-Dist: anyio; extra == 'async'
